Metadata-Version: 2.1
Name: gallos
Version: 0.0.7
Summary: A sample package
Home-page: https://github.com/Stegallo/gallos
License: UNKNOWN
Platform: UNKNOWN
Classifier: Programming Language :: Python :: 3
Classifier: License :: OSI Approved :: MIT License
Classifier: Operating System :: OS Independent
